[
    {
        "bcode": 1,
        "cnum": 15,
        "content": "\uc774 \ud6c4\uc5d0 \uc5ec\ud638\uc640\uc758 \ub9d0\uc500\uc774 \ud658\uc0c1 \uc911\uc5d0 \uc544\ube0c\ub78c\uc5d0\uac8c \uc784\ud558\uc5ec \uc774\ub974\uc2dc\ub418 \uc544\ube0c\ub78c\uc544 \ub450\ub824\uc6cc\ud558\uc9c0 \ub9d0\ub77c \ub098\ub294 \ub124 \ubc29\ud328\uc694 \ub108\uc758 \uc9c0\uadf9\ud788 \ud070 \uc0c1\uae09\uc774\ub2c8\ub77c",
        "vcode": "GAE",
        "vnum": 1
    },
    {
        "bcode": 1,
        "cnum": 15,
        "content": "\uc544\ube0c\ub78c\uc774 \uc774\ub974\ub418 \uc8fc \uc5ec\ud638\uc640\uc5ec \ubb34\uc5c7\uc744 \ub0b4\uac8c \uc8fc\uc2dc\ub824 \ud558\ub098\uc774\uae4c \ub098\ub294 \uc790\uc2dd\uc774 \uc5c6\uc0ac\uc624\ub2c8 \ub098\uc758 \uc0c1\uc18d\uc790\ub294 \uc774 \ub2e4\uba54\uc139 \uc0ac\ub78c \uc5d8\ub9ac\uc5d0\uc140\uc774\ub2c8\uc774\ub2e4",
        "vcode": "GAE",
        "vnum": 2
    },
    {
        "bcode": 1,
        "cnum": 15,
        "content": "\uc544\ube0c\ub78c\uc774 \ub610 \uc774\ub974\ub418 \uc8fc\uaed8\uc11c \ub0b4\uac8c \uc528\ub97c \uc8fc\uc9c0 \uc544\ub2c8\ud558\uc168\uc73c\ub2c8 \ub0b4 \uc9d1\uc5d0\uc11c \uae38\ub9b0 \uc790\uac00 \ub0b4 \uc0c1\uc18d\uc790\uac00 \ub420 \uac83\uc774\ub2c8\uc774\ub2e4",
        "vcode": "GAE",
        "vnum": 3
    },
    {
        "bcode": 1,
        "cnum": 15,
        "content": "\uc5ec\ud638\uc640\uc758 \ub9d0\uc500\uc774 \uadf8\uc5d0\uac8c \uc784\ud558\uc5ec \uc774\ub974\uc2dc\ub418 \uadf8 \uc0ac\ub78c\uc774 \ub124 \uc0c1\uc18d\uc790\uac00 \uc544\ub2c8\ub77c \ub124 \ubab8\uc5d0\uc11c \ub0a0 \uc790\uac00 \ub124 \uc0c1\uc18d\uc790\uac00 \ub418\ub9ac\ub77c \ud558\uc2dc\uace0",
        "vcode": "GAE",
        "vnum": 4
    },
    {
        "bcode": 1,
        "cnum": 15,
        "content": "\uadf8\ub97c \uc774\ub04c\uace0 \ubc16\uc73c\ub85c \ub098\uac00 \uc774\ub974\uc2dc\ub418 \ud558\ub298\uc744 \uc6b0\ub7ec\ub7ec \ubb47\ubcc4\uc744 \uc140 \uc218 \uc788\ub098 \ubcf4\ub77c \ub610 \uadf8\uc5d0\uac8c \uc774\ub974\uc2dc\ub418 \ub124 \uc790\uc190\uc774 \uc774\uc640 \uac19\uc73c\ub9ac\ub77c",
        "vcode": "GAE",
        "vnum": 5
    },
    {
        "bcode": 1,
        "cnum": 15,
        "content": "\uc544\ube0c\ub78c\uc774 \uc5ec\ud638\uc640\ub97c \ubbff\uc73c\ub2c8 \uc5ec\ud638\uc640\uaed8\uc11c \uc774\ub97c \uadf8\uc758 \uc758\ub85c \uc5ec\uae30\uc2dc\uace0",
        "vcode": "GAE",
        "vnum": 6
    },
    {
        "bcode": 1,
        "cnum": 15,
        "content": "\ub610 \uadf8\uc5d0\uac8c \uc774\ub974\uc2dc\ub418 \ub098\ub294 \uc774 \ub545\uc744 \ub124\uac8c \uc8fc\uc5b4 \uc18c\uc720\ub97c \uc0bc\uac8c \ud558\ub824\uace0 \ub108\ub97c \uac08\ub300\uc544\uc778\uc758 \uc6b0\ub974\uc5d0\uc11c \uc774\ub04c\uc5b4 \ub0b8 \uc5ec\ud638\uc640\ub2c8\ub77c",
        "vcode": "GAE",
        "vnum": 7
    },
    {
        "bcode": 1,
        "cnum": 15,
        "content": "\uadf8\uac00 \uc774\ub974\ub418 \uc8fc \uc5ec\ud638\uc640\uc5ec \ub0b4\uac00 \uc774 \ub545\uc744 \uc18c\uc720\ub85c \ubc1b\uc744 \uac83\uc744 \ubb34\uc5c7\uc73c\ub85c \uc54c\ub9ac\uc774\uae4c",
        "vcode": "GAE",
        "vnum": 8
    },
    {
        "bcode": 1,
        "cnum": 15,
        "content": "\uc5ec\ud638\uc640\uaed8\uc11c \uadf8\uc5d0\uac8c \uc774\ub974\uc2dc\ub418 \ub098\ub97c \uc704\ud558\uc5ec \uc0bc \ub144 \ub41c \uc554\uc18c\uc640 \uc0bc \ub144 \ub41c \uc554\uc5fc\uc18c\uc640 \uc0bc \ub144 \ub41c \uc22b\uc591\uacfc \uc0b0\ube44\ub458\uae30\uc640 \uc9d1\ube44\ub458\uae30 \uc0c8\ub07c\ub97c \uac00\uc838\uc62c\uc9c0\ub2c8\ub77c",
        "vcode": "GAE",
        "vnum": 9
    },
    {
        "bcode": 1,
        "cnum": 15,
        "content": "\uc544\ube0c\ub78c\uc774 \uadf8 \ubaa8\ub4e0 \uac83\uc744 \uac00\uc838\ub2e4\uac00 \uadf8 \uc911\uac04\uc744 \ucabc\uac1c\uace0 \uadf8 \ucabc\uac20 \uac83\uc744 \ub9c8\uc8fc \ub300\ud558\uc5ec \ub193\uace0 \uadf8 \uc0c8\ub294 \ucabc\uac1c\uc9c0 \uc544\ub2c8\ud558\uc600\uc73c\uba70",
        "vcode": "GAE",
        "vnum": 10
    },
    {
        "bcode": 1,
        "cnum": 15,
        "content": "\uc194\uac1c\uac00 \uadf8 \uc0ac\uccb4 \uc704\uc5d0 \ub0b4\ub9b4 \ub54c\uc5d0\ub294 \uc544\ube0c\ub78c\uc774 \ucad3\uc558\ub354\ub77c",
        "vcode": "GAE",
        "vnum": 11
    },
    {
        "bcode": 1,
        "cnum": 15,
        "content": "\ud574 \uc9c8 \ub54c\uc5d0 \uc544\ube0c\ub78c\uc5d0\uac8c \uae4a\uc740 \uc7a0\uc774 \uc784\ud558\uace0 \ud070 \ud751\uc554\uacfc \ub450\ub824\uc6c0\uc774 \uadf8\uc5d0\uac8c \uc784\ud558\uc600\ub354\ub2c8",
        "vcode": "GAE",
        "vnum": 12
    },
    {
        "bcode": 1,
        "cnum": 15,
        "content": "\uc5ec\ud638\uc640\uaed8\uc11c \uc544\ube0c\ub78c\uc5d0\uac8c \uc774\ub974\uc2dc\ub418 \ub108\ub294 \ubc18\ub4dc\uc2dc \uc54c\ub77c \ub124 \uc790\uc190\uc774 \uc774\ubc29\uc5d0\uc11c \uac1d\uc774 \ub418\uc5b4 \uadf8\ub4e4\uc744 \uc12c\uae30\uaca0\uace0 \uadf8\ub4e4\uc740 \uc0ac\ubc31 \ub144 \ub3d9\uc548 \ub124 \uc790\uc190\uc744 \uad34\ub86d\ud788\ub9ac\ub2c8",
        "vcode": "GAE",
        "vnum": 13
    },
    {
        "bcode": 1,
        "cnum": 15,
        "content": "\uadf8\ub4e4\uc774 \uc12c\uae30\ub294 \ub098\ub77c\ub97c \ub0b4\uac00 \uc9d5\ubc8c\ud560\uc9c0\uba70 \uadf8 \ud6c4\uc5d0 \ub124 \uc790\uc190\uc774 \ud070 \uc7ac\ubb3c\uc744 \uc774\ub04c\uace0 \ub098\uc624\ub9ac\ub77c",
        "vcode": "GAE",
        "vnum": 14
    },
    {
        "bcode": 1,
        "cnum": 15,
        "content": "\ub108\ub294 \uc7a5\uc218\ud558\ub2e4\uac00 \ud3c9\uc548\ud788 \uc870\uc0c1\uc5d0\uac8c\ub85c \ub3cc\uc544\uac00 \uc7a5\uc0ac\ub420 \uac83\uc774\uc694",
        "vcode": "GAE",
        "vnum": 15
    },
    {
        "bcode": 1,
        "cnum": 15,
        "content": "\ub124 \uc790\uc190\uc740 \uc0ac\ub300 \ub9cc\uc5d0 \uc774 \ub545\uc73c\ub85c \ub3cc\uc544\uc624\ub9ac\ub2c8 \uc774\ub294 \uc544\ubaa8\ub9ac \uc871\uc18d\uc758 \uc8c4\uc545\uc774 \uc544\uc9c1 \uac00\ub4dd \ucc28\uc9c0 \uc544\ub2c8\ud568\uc774\ub2c8\ub77c \ud558\uc2dc\ub354\ub2c8",
        "vcode": "GAE",
        "vnum": 16
    },
    {
        "bcode": 1,
        "cnum": 15,
        "content": "\ud574\uac00 \uc838\uc11c \uc5b4\ub450\uc6b8 \ub54c\uc5d0 \uc5f0\uae30 \ub098\ub294 \ud654\ub85c\uac00 \ubcf4\uc774\uba70 \ud0c0\ub294 \ud683\ubd88\uc774 \ucabc\uac20 \uace0\uae30 \uc0ac\uc774\ub85c \uc9c0\ub098\ub354\ub77c",
        "vcode": "GAE",
        "vnum": 17
    },
    {
        "bcode": 1,
        "cnum": 15,
        "content": "\uadf8 \ub0a0\uc5d0 \uc5ec\ud638\uc640\uaed8\uc11c \uc544\ube0c\ub78c\uacfc \ub354\ubd88\uc5b4 \uc5b8\uc57d\uc744 \uc138\uc6cc \uc774\ub974\uc2dc\ub418 \ub0b4\uac00 \uc774 \ub545\uc744 \uc560\uad7d \uac15\uc5d0\uc11c\ubd80\ud130 \uadf8 \ud070 \uac15 \uc720\ube0c\ub77c\ub370\uae4c\uc9c0 \ub124 \uc790\uc190\uc5d0\uac8c \uc8fc\ub178\ub2c8",
        "vcode": "GAE",
        "vnum": 18
    },
    {
        "bcode": 1,
        "cnum": 15,
        "content": "\uace7 \uac90 \uc871\uc18d\uacfc \uadf8\ub2c8\uc2a4 \uc871\uc18d\uacfc \uac13\ubaac \uc871\uc18d\uacfc",
        "vcode": "GAE",
        "vnum": 19
    },
    {
        "bcode": 1,
        "cnum": 15,
        "content": "\ud5f7 \uc871\uc18d\uacfc \ube0c\ub9ac\uc2a4 \uc871\uc18d\uacfc \ub974\ubc14 \uc871\uc18d\uacfc",
        "vcode": "GAE",
        "vnum": 20
    },
    {
        "bcode": 1,
        "cnum": 15,
        "content": "\uc544\ubaa8\ub9ac \uc871\uc18d\uacfc \uac00\ub098\uc548 \uc871\uc18d\uacfc \uae30\ub974\uac00\uc2a4 \uc871\uc18d\uacfc \uc5ec\ubd80\uc2a4 \uc871\uc18d\uc758 \ub545\uc774\ub2c8\ub77c \ud558\uc168\ub354\ub77c",
        "vcode": "GAE",
        "vnum": 21
    }
]