[
    {
        "bcode": 21,
        "cnum": 11,
        "content": "\ub108\ub294 \ub124 \ub5a1\uc744 \ubb3c \uc704\uc5d0 \ub358\uc838\ub77c \uc5ec\ub7ec \ub0a0 \ud6c4\uc5d0 \ub3c4\ub85c \ucc3e\uc73c\ub9ac\ub77c",
        "vcode": "GAE",
        "vnum": 1
    },
    {
        "bcode": 21,
        "cnum": 11,
        "content": "\uc77c\uacf1\uc5d0\uac8c\ub098 \uc5ec\ub35f\uc5d0\uac8c \ub098\ub220 \uc904\uc9c0\uc5b4\ub2e4 \ubb34\uc2a8 \uc7ac\uc559\uc774 \ub545\uc5d0 \uc784\ud560\ub294\uc9c0 \ub124\uac00 \uc54c\uc9c0 \ubabb\ud568\uc774\ub2c8\ub77c",
        "vcode": "GAE",
        "vnum": 2
    },
    {
        "bcode": 21,
        "cnum": 11,
        "content": "\uad6c\ub984\uc5d0 \ube44\uac00 \uac00\ub4dd\ud558\uba74 \ub545\uc5d0 \uc3df\uc544\uc9c0\uba70 \ub098\ubb34\uac00 \ub0a8\uc73c\ub85c\ub098 \ubd81\uc73c\ub85c\ub098 \uc4f0\ub7ec\uc9c0\uba74 \uadf8 \uc4f0\ub7ec\uc9c4 \uacf3\uc5d0 \uadf8\ub0e5 \uc788\uc73c\ub9ac\ub77c",
        "vcode": "GAE",
        "vnum": 3
    },
    {
        "bcode": 21,
        "cnum": 11,
        "content": "\ud48d\uc138\ub97c \uc0b4\ud3b4\ubcf4\ub294 \uc790\ub294 \ud30c\uc885\ud558\uc9c0 \ubabb\ud560 \uac83\uc774\uc694 \uad6c\ub984\ub9cc \ubc14\ub77c\ubcf4\ub294 \uc790\ub294 \uac70\ub450\uc9c0 \ubabb\ud558\ub9ac\ub77c",
        "vcode": "GAE",
        "vnum": 4
    },
    {
        "bcode": 21,
        "cnum": 11,
        "content": "\ubc14\ub78c\uc758 \uae38\uc774 \uc5b4\ub5a0\ud568\uacfc \uc544\uc774 \ubc34 \uc790\uc758 \ud0dc\uc5d0\uc11c \ubf08\uac00 \uc5b4\ub5bb\uac8c \uc790\ub77c\ub294\uc9c0\ub97c \ub124\uac00 \uc54c\uc9c0 \ubabb\ud568 \uac19\uc774 \ub9cc\uc0ac\ub97c \uc131\ucde8\ud558\uc2dc\ub294 \ud558\ub098\ub2d8\uc758 \uc77c\uc744 \ub124\uac00 \uc54c\uc9c0 \ubabb\ud558\ub290\ub2c8\ub77c",
        "vcode": "GAE",
        "vnum": 5
    },
    {
        "bcode": 21,
        "cnum": 11,
        "content": "\ub108\ub294 \uc544\uce68\uc5d0 \uc528\ub97c \ubfcc\ub9ac\uace0 \uc800\ub141\uc5d0\ub3c4 \uc190\uc744 \ub193\uc9c0 \ub9d0\ub77c \uc774\uac83\uc774 \uc798 \ub420\ub294\uc9c0, \uc800\uac83\uc774 \uc798 \ub420\ub294\uc9c0, \ud639 \ub458\uc774 \ub2e4 \uc798 \ub420\ub294\uc9c0 \uc54c\uc9c0 \ubabb\ud568\uc774\ub2c8\ub77c",
        "vcode": "GAE",
        "vnum": 6
    },
    {
        "bcode": 21,
        "cnum": 11,
        "content": "\ube5b\uc740 \uc2e4\ub85c \uc544\ub984\ub2e4\uc6b4 \uac83\uc774\ub77c \ub208\uc73c\ub85c \ud574\ub97c \ubcf4\ub294 \uac83\uc774 \uc990\uac70\uc6b4 \uc77c\uc774\ub85c\ub2e4",
        "vcode": "GAE",
        "vnum": 7
    },
    {
        "bcode": 21,
        "cnum": 11,
        "content": "\uc0ac\ub78c\uc774 \uc5ec\ub7ec \ud574\ub97c \uc0b4\uba74 \ud56d\uc0c1 \uc990\uac70\uc6cc\ud560\uc9c0\ub85c\ub2e4 \uadf8\ub7ec\ub098 \uce84\uce84\ud55c \ub0a0\ub4e4\uc774 \ub9ce\uc73c\ub9ac\ub2c8 \uadf8 \ub0a0\ub4e4\uc744 \uc0dd\uac01\ud560\uc9c0\ub85c\ub2e4 \ub2e4\uac00\uc62c \uc77c\uc740 \ub2e4 \ud5db\ub418\ub3c4\ub2e4",
        "vcode": "GAE",
        "vnum": 8
    },
    {
        "bcode": 21,
        "cnum": 11,
        "content": "\uccad\ub144\uc774\uc5ec \ub124 \uc5b4\ub9b0 \ub54c\ub97c \uc990\uac70\uc6cc\ud558\uba70 \ub124 \uccad\ub144\uc758 \ub0a0\ub4e4\uc744 \ub9c8\uc74c\uc5d0 \uae30\ubed0\ud558\uc5ec \ub9c8\uc74c\uc5d0 \uc6d0\ud558\ub294 \uae38\ub4e4\uacfc \ub124 \ub208\uc774 \ubcf4\ub294 \ub300\ub85c \ud589\ud558\ub77c \uadf8\ub7ec\ub098 \ud558\ub098\ub2d8\uc774 \uc774 \ubaa8\ub4e0 \uc77c\ub85c \ub9d0\ubbf8\uc554\uc544 \ub108\ub97c \uc2ec\ud310\ud558\uc2e4 \uc904 \uc54c\ub77c",
        "vcode": "GAE",
        "vnum": 9
    },
    {
        "bcode": 21,
        "cnum": 11,
        "content": "\uadf8\ub7f0\uc989 \uadfc\uc2ec\uc774 \ub124 \ub9c8\uc74c\uc5d0\uc11c \ub5a0\ub098\uac8c \ud558\uba70 \uc545\uc774 \ub124 \ubab8\uc5d0\uc11c \ubb3c\ub7ec\uac00\uac8c \ud558\ub77c \uc5b4\ub9b4 \ub54c\uc640 \uac80\uc740 \uba38\ub9ac\uc758 \uc2dc\uc808\uc774 \ub2e4 \ud5db\ub418\ub2c8\ub77c",
        "vcode": "GAE",
        "vnum": 10
    }
]