[
    {
        "bcode": 23,
        "cnum": 31,
        "content": "\ub3c4\uc6c0\uc744 \uad6c\ud558\ub7ec \uc560\uad7d\uc73c\ub85c \ub0b4\ub824\uac00\ub294 \uc790\ub4e4\uc740 \ud654 \uc788\uc744\uc9c4\uc800 \uadf8\ub4e4\uc740 \ub9d0\uc744 \uc758\uc9c0\ud558\uba70 \ubcd1\uac70\uc758 \ub9ce\uc74c\uacfc \ub9c8\ubcd1\uc758 \uc2ec\ud788 \uac15\ud568\uc744 \uc758\uc9c0\ud558\uace0 \uc774\uc2a4\ub77c\uc5d8\uc758 \uac70\ub8e9\ud558\uc2e0 \uc774\ub97c \uc559\ubaa8\ud558\uc9c0 \uc544\ub2c8\ud558\uba70 \uc5ec\ud638\uc640\ub97c \uad6c\ud558\uc9c0 \uc544\ub2c8\ud558\ub098\ub2c8",
        "vcode": "GAE",
        "vnum": 1
    },
    {
        "bcode": 23,
        "cnum": 31,
        "content": "\uc5ec\ud638\uc640\uaed8\uc11c\ub3c4 \uc9c0\ud61c\ub85c\uc6b0\uc2e0\uc989 \uc7ac\uc559\uc744 \ub0b4\ub9ac\uc2e4 \uac83\uc774\ub77c \uadf8\uc758 \ub9d0\uc500\ub4e4\uc744 \ubcc0\ud558\uac8c \ud558\uc9c0 \uc544\ub2c8\ud558\uc2dc\uace0 \uc77c\uc5b4\ub098\uc0ac \uc545\ud589\ud558\ub294 \uc790\ub4e4\uc758 \uc9d1\uc744 \uce58\uc2dc\uba70 \ud589\uc545\uc744 \ub3d5\ub294 \uc790\ub4e4\uc744 \uce58\uc2dc\ub9ac\ub2c8",
        "vcode": "GAE",
        "vnum": 2
    },
    {
        "bcode": 23,
        "cnum": 31,
        "content": "\uc560\uad7d\uc740 \uc0ac\ub78c\uc774\uc694 \uc2e0\uc774 \uc544\ub2c8\uba70 \uadf8\ub4e4\uc758 \ub9d0\ub4e4\uc740 \uc721\uccb4\uc694 \uc601\uc774 \uc544\ub2c8\ub77c \uc5ec\ud638\uc640\uaed8\uc11c \uadf8\uc758 \uc190\uc744 \ud3b4\uc2dc\uba74 \ub3d5\ub294 \uc790\ub3c4 \ub118\uc5b4\uc9c0\uba70 \ub3c4\uc6c0\uc744 \ubc1b\ub294 \uc790\ub3c4 \uc5ce\ub4dc\ub7ec\uc838\uc11c \ub2e4 \ud568\uaed8 \uba78\ub9dd\ud558\ub9ac\ub77c",
        "vcode": "GAE",
        "vnum": 3
    },
    {
        "bcode": 23,
        "cnum": 31,
        "content": "\uc5ec\ud638\uc640\uaed8\uc11c \uc774\uac19\uc774 \ub0b4\uac8c \uc774\ub974\uc2dc\ub418 \ud070 \uc0ac\uc790\ub098 \uc80a\uc740 \uc0ac\uc790\uac00 \uc790\uae30\uc758 \uba39\uc774\ub97c \uc6c0\ud0a4\uace0 \uc73c\ub974\ub801\uac70\ub9b4 \ub54c\uc5d0 \uadf8\uac83\uc744 \uce58\ub824\uace0 \uc5ec\ub7ec \ubaa9\uc790\ub97c \ubd88\ub7ec \uc654\ub2e4 \ud560\uc9c0\ub77c\ub3c4 \uadf8\uac83\uc774 \uadf8\ub4e4\uc758 \uc18c\ub9ac\ub85c \ub9d0\ubbf8\uc554\uc544 \ub180\ub77c\uc9c0 \uc544\ub2c8\ud560 \uac83\uc774\uc694 \uadf8\ub4e4\uc758 \ub5a0\ub4e6\uc73c\ub85c \ub9d0\ubbf8\uc554\uc544 \uad74\ubcf5\ud558\uc9c0 \uc544\ub2c8\ud560 \uac83\uc774\ub77c \uc774\uc640 \uac19\uc774 \ub098 \ub9cc\uad70\uc758 \uc5ec\ud638\uc640\uac00 \uac15\ub9bc\ud558\uc5ec \uc2dc\uc628 \uc0b0\uacfc \uadf8 \uc5b8\ub355\uc5d0\uc11c \uc2f8\uc6b8 \uac83\uc774\ub77c",
        "vcode": "GAE",
        "vnum": 4
    },
    {
        "bcode": 23,
        "cnum": 31,
        "content": "\uc0c8\uac00 \ub0a0\uac1c \uce58\uba70 \uadf8 \uc0c8\ub07c\ub97c \ubcf4\ud638\ud568 \uac19\uc774 \ub098 \ub9cc\uad70\uc758 \uc5ec\ud638\uc640\uac00 \uc608\ub8e8\uc0b4\ub818\uc744 \ubcf4\ud638\ud560 \uac83\uc774\ub77c \uadf8\uac83\uc744 \ud638\uc704\ud558\uba70 \uac74\uc9c0\uba70 \ub6f0\uc5b4\ub118\uc5b4 \uad6c\uc6d0\ud558\ub9ac\ub77c \ud558\uc168\ub290\ub2c8\ub77c",
        "vcode": "GAE",
        "vnum": 5
    },
    {
        "bcode": 23,
        "cnum": 31,
        "content": "\uc774\uc2a4\ub77c\uc5d8 \uc790\uc190\ub4e4\uc544 \ub108\ud76c\ub294 \uc2ec\ud788 \uac70\uc5ed\ud558\ub358 \uc790\uc5d0\uac8c\ub85c \ub3cc\uc544\uc624\ub77c",
        "vcode": "GAE",
        "vnum": 6
    },
    {
        "bcode": 23,
        "cnum": 31,
        "content": "\ub108\ud76c\uac00 \uc790\uae30 \uc190\uc73c\ub85c \ub9cc\ub4e4\uc5b4 \ubc94\uc8c4\ud55c \uc740 \uc6b0\uc0c1, \uae08 \uc6b0\uc0c1\uc744 \uadf8 \ub0a0\uc5d0\ub294 \uac01 \uc0ac\ub78c\uc774 \ub358\uc838 \ubc84\ub9b4 \uac83\uc774\uba70",
        "vcode": "GAE",
        "vnum": 7
    },
    {
        "bcode": 23,
        "cnum": 31,
        "content": "\uc557\uc218\ub974\ub294 \uce7c\uc5d0 \uc5ce\ub4dc\ub7ec\uc9c8 \uac83\uc774\ub098 \uc0ac\ub78c\uc758 \uce7c\ub85c \ub9d0\ubbf8\uc554\uc74c\uc774 \uc544\ub2c8\uaca0\uace0 \uce7c\uc5d0 \uc0bc\ucf1c\uc9c8 \uac83\uc774\ub098 \uc0ac\ub78c\uc758 \uce7c\ub85c \ub9d0\ubbf8\uc554\uc74c\uc774 \uc544\ub2d0 \uac83\uc774\uba70 \uadf8\ub294 \uce7c \uc55e\uc5d0\uc11c \ub3c4\ub9dd\ud560 \uac83\uc774\uc694 \uadf8\uc758 \uc7a5\uc815\ub4e4\uc740 \ubcf5\uc5ed\ud558\ub294 \uc790\uac00 \ub420 \uac83\uc774\ub77c",
        "vcode": "GAE",
        "vnum": 8
    },
    {
        "bcode": 23,
        "cnum": 31,
        "content": "\uadf8\uc758 \ubc18\uc11d\uc740 \ub450\ub824\uc6c0\uc73c\ub85c \ub9d0\ubbf8\uc554\uc544 \ubb3c\ub7ec\uac00\uaca0\uace0 \uadf8\uc758 \uace0\uad00\ub4e4\uc740 \uae30\uce58\ub85c \ub9d0\ubbf8\uc554\uc544 \ub180\ub77c\ub9ac\ub77c \uc774\ub294 \uc5ec\ud638\uc640\uc758 \ub9d0\uc500\uc774\ub77c \uc5ec\ud638\uc640\uc758 \ubd88\uc740 \uc2dc\uc628\uc5d0 \uc788\uace0 \uc5ec\ud638\uc640\uc758 \ud480\ubb34\ub294 \uc608\ub8e8\uc0b4\ub818\uc5d0 \uc788\ub290\ub2c8\ub77c",
        "vcode": "GAE",
        "vnum": 9
    }
]