[
    {
        "bcode": 19,
        "cnum": 93,
        "content": "The LORD reigns, he is robed in majesty; the LORD is robed in majesty and is armed with strength. The world is firmly established; it cannot be moved.",
        "vcode": "NIV",
        "vnum": 1
    },
    {
        "bcode": 19,
        "cnum": 93,
        "content": "Your throne was established long ago; you are from all eternity.",
        "vcode": "NIV",
        "vnum": 2
    },
    {
        "bcode": 19,
        "cnum": 93,
        "content": "The seas have lifted up, O LORD, the seas have lifted up their voice; the seas have lifted up their pounding waves.",
        "vcode": "NIV",
        "vnum": 3
    },
    {
        "bcode": 19,
        "cnum": 93,
        "content": "Mightier than the thunder of the great waters, mightier than the breakers of the sea-- the LORD on high is mighty.",
        "vcode": "NIV",
        "vnum": 4
    },
    {
        "bcode": 19,
        "cnum": 93,
        "content": "Your statutes stand firm; holiness adorns your house for endless days, O LORD.",
        "vcode": "NIV",
        "vnum": 5
    }
]