[
    {
        "bcode": 66,
        "cnum": 3,
        "content": "\uc0ac\ub370 \uad50\ud68c\uc758 \uc0ac\uc790\uc5d0\uac8c \ud3b8\uc9c0\ud558\ub77c \ud558\ub098\ub2d8\uc758 \uc77c\uacf1 \uc601\uacfc \uc77c\uacf1 \ubcc4\uc744 \uac00\uc9c0\uc2e0 \uc774\uac00 \uc774\ub974\uc2dc\ub418 \ub0b4\uac00 \ub124 \ud589\uc704\ub97c \uc544\ub178\ub2c8 \ub124\uac00 \uc0b4\uc558\ub2e4 \ud558\ub294 \uc774\ub984\uc740 \uac00\uc84c\uc73c\ub098 \uc8fd\uc740 \uc790\ub85c\ub2e4",
        "vcode": "GAE",
        "vnum": 1
    },
    {
        "bcode": 66,
        "cnum": 3,
        "content": "\ub108\ub294 \uc77c\uae68\uc5b4 \uadf8 \ub0a8\uc740 \ubc14 \uc8fd\uac8c \ub41c \uac83\uc744 \uad73\uac74\ud558\uac8c \ud558\ub77c \ub0b4 \ud558\ub098\ub2d8 \uc55e\uc5d0 \ub124 \ud589\uc704\uc758 \uc628\uc804\ud55c \uac83\uc744 \ucc3e\uc9c0 \ubabb\ud558\uc600\ub178\ub2c8",
        "vcode": "GAE",
        "vnum": 2
    },
    {
        "bcode": 66,
        "cnum": 3,
        "content": "\uadf8\ub7ec\ubbc0\ub85c \ub124\uac00 \uc5b4\ub5bb\uac8c \ubc1b\uc558\uc73c\uba70 \uc5b4\ub5bb\uac8c \ub4e4\uc5c8\ub294\uc9c0 \uc0dd\uac01\ud558\uace0 \uc9c0\ucf1c \ud68c\uac1c\ud558\ub77c \ub9cc\uc77c \uc77c\uae68\uc9c0 \uc544\ub2c8\ud558\uba74 \ub0b4\uac00 \ub3c4\ub451 \uac19\uc774 \uc774\ub974\ub9ac\ub2c8 \uc5b4\ub290 \ub54c\uc5d0 \ub124\uac8c \uc774\ub97c\ub294\uc9c0 \ub124\uac00 \uc54c\uc9c0 \ubabb\ud558\ub9ac\ub77c",
        "vcode": "GAE",
        "vnum": 3
    },
    {
        "bcode": 66,
        "cnum": 3,
        "content": "\uadf8\ub7ec\ub098 \uc0ac\ub370\uc5d0 \uadf8 \uc637\uc744 \ub354\ub7fd\ud788\uc9c0 \uc544\ub2c8\ud55c \uc790 \uba87 \uba85\uc774 \ub124\uac8c \uc788\uc5b4 \ud770 \uc637\uc744 \uc785\uace0 \ub098\uc640 \ud568\uaed8 \ub2e4\ub2c8\ub9ac\ub2c8 \uadf8\ub4e4\uc740 \ud569\ub2f9\ud55c \uc790\uc778 \uc5f0\uace0\ub77c",
        "vcode": "GAE",
        "vnum": 4
    },
    {
        "bcode": 66,
        "cnum": 3,
        "content": "\uc774\uae30\ub294 \uc790\ub294 \uc774\uc640 \uac19\uc774 \ud770 \uc637\uc744 \uc785\uc744 \uac83\uc774\uc694 \ub0b4\uac00 \uadf8 \uc774\ub984\uc744 \uc0dd\uba85\ucc45\uc5d0\uc11c \uacb0\ucf54 \uc9c0\uc6b0\uc9c0 \uc544\ub2c8\ud558\uace0 \uadf8 \uc774\ub984\uc744 \ub0b4 \uc544\ubc84\uc9c0 \uc55e\uacfc \uadf8\uc758 \ucc9c\uc0ac\ub4e4 \uc55e\uc5d0\uc11c \uc2dc\uc778\ud558\ub9ac\ub77c",
        "vcode": "GAE",
        "vnum": 5
    },
    {
        "bcode": 66,
        "cnum": 3,
        "content": "\uadc0 \uc788\ub294 \uc790\ub294 \uc131\ub839\uc774 \uad50\ud68c\ub4e4\uc5d0\uac8c \ud558\uc2dc\ub294 \ub9d0\uc500\uc744 \ub4e4\uc744\uc9c0\uc5b4\ub2e4",
        "vcode": "GAE",
        "vnum": 6
    },
    {
        "bcode": 66,
        "cnum": 3,
        "content": "\ube4c\ub77c\ub378\ube44\uc544 \uad50\ud68c\uc758 \uc0ac\uc790\uc5d0\uac8c \ud3b8\uc9c0\ud558\ub77c \uac70\ub8e9\ud558\uace0 \uc9c4\uc2e4\ud558\uc0ac \ub2e4\uc717\uc758 \uc5f4\uc1e0\ub97c \uac00\uc9c0\uc2e0 \uc774 \uace7 \uc5f4\uba74 \ub2eb\uc744 \uc0ac\ub78c\uc774 \uc5c6\uace0 \ub2eb\uc73c\uba74 \uc5f4 \uc0ac\ub78c\uc774 \uc5c6\ub294 \uadf8\uac00 \uc774\ub974\uc2dc\ub418",
        "vcode": "GAE",
        "vnum": 7
    },
    {
        "bcode": 66,
        "cnum": 3,
        "content": "\ubcfc\uc9c0\uc5b4\ub2e4 \ub0b4\uac00 \ub124 \uc55e\uc5d0 \uc5f4\ub9b0 \ubb38\uc744 \ub450\uc5c8\uc73c\ub418 \ub2a5\ud788 \ub2eb\uc744 \uc0ac\ub78c\uc774 \uc5c6\uc73c\ub9ac\ub77c \ub0b4\uac00 \ub124 \ud589\uc704\ub97c \uc544\ub178\ub2c8 \ub124\uac00 \uc791\uc740 \ub2a5\ub825\uc744 \uac00\uc9c0\uace0\uc11c\ub3c4 \ub0b4 \ub9d0\uc744 \uc9c0\ud0a4\uba70 \ub0b4 \uc774\ub984\uc744 \ubc30\ubc18\ud558\uc9c0 \uc544\ub2c8\ud558\uc600\ub3c4\ub2e4",
        "vcode": "GAE",
        "vnum": 8
    },
    {
        "bcode": 66,
        "cnum": 3,
        "content": "\ubcf4\ub77c \uc0ac\ud0c4\uc758 \ud68c\ub2f9 \uace7 \uc790\uce6d \uc720\ub300\uc778\uc774\ub77c \ud558\ub098 \uadf8\ub807\uc9c0 \uc544\ub2c8\ud558\uace0 \uac70\uc9d3\ub9d0 \ud558\ub294 \uc790\ub4e4 \uc911\uc5d0\uc11c \uba87\uc744 \ub124\uac8c \uc8fc\uc5b4 \uadf8\ub4e4\ub85c \uc640\uc11c \ub124 \ubc1c \uc55e\uc5d0 \uc808\ud558\uac8c \ud558\uace0 \ub0b4\uac00 \ub108\ub97c \uc0ac\ub791\ud558\ub294 \uc904\uc744 \uc54c\uac8c \ud558\ub9ac\ub77c",
        "vcode": "GAE",
        "vnum": 9
    },
    {
        "bcode": 66,
        "cnum": 3,
        "content": "\ub124\uac00 \ub098\uc758 \uc778\ub0b4\uc758 \ub9d0\uc500\uc744 \uc9c0\ucf30\uc740\uc989 \ub0b4\uac00 \ub610\ud55c \ub108\ub97c \uc9c0\ucf1c \uc2dc\ud5d8\uc758 \ub54c\ub97c \uba74\ud558\uac8c \ud558\ub9ac\ub2c8 \uc774\ub294 \uc7a5\ucc28 \uc628 \uc138\uc0c1\uc5d0 \uc784\ud558\uc5ec \ub545\uc5d0 \uac70\ud558\ub294 \uc790\ub4e4\uc744 \uc2dc\ud5d8\ud560 \ub54c\ub77c",
        "vcode": "GAE",
        "vnum": 10
    },
    {
        "bcode": 66,
        "cnum": 3,
        "content": "\ub0b4\uac00 \uc18d\ud788 \uc624\ub9ac\ub2c8 \ub124\uac00 \uac00\uc9c4 \uac83\uc744 \uad73\uac8c \uc7a1\uc544 \uc544\ubb34\ub3c4 \ub124 \uba74\ub958\uad00\uc744 \ube7c\uc557\uc9c0 \ubabb\ud558\uac8c \ud558\ub77c",
        "vcode": "GAE",
        "vnum": 11
    },
    {
        "bcode": 66,
        "cnum": 3,
        "content": "\uc774\uae30\ub294 \uc790\ub294 \ub0b4 \ud558\ub098\ub2d8 \uc131\uc804\uc5d0 \uae30\ub465\uc774 \ub418\uac8c \ud558\ub9ac\ub2c8 \uadf8\uac00 \uacb0\ucf54 \ub2e4\uc2dc \ub098\uac00\uc9c0 \uc544\ub2c8\ud558\ub9ac\ub77c \ub0b4\uac00 \ud558\ub098\ub2d8\uc758 \uc774\ub984\uacfc \ud558\ub098\ub2d8\uc758 \uc131 \uace7 \ud558\ub298\uc5d0\uc11c \ub0b4 \ud558\ub098\ub2d8\uaed8\ub85c\ubd80\ud130 \ub0b4\ub824\uc624\ub294 \uc0c8 \uc608\ub8e8\uc0b4\ub818\uc758 \uc774\ub984\uacfc \ub098\uc758 \uc0c8 \uc774\ub984\uc744 \uadf8\uc774 \uc704\uc5d0 \uae30\ub85d\ud558\ub9ac\ub77c",
        "vcode": "GAE",
        "vnum": 12
    },
    {
        "bcode": 66,
        "cnum": 3,
        "content": "\uadc0 \uc788\ub294 \uc790\ub294 \uc131\ub839\uc774 \uad50\ud68c\ub4e4\uc5d0\uac8c \ud558\uc2dc\ub294 \ub9d0\uc500\uc744 \ub4e4\uc744\uc9c0\uc5b4\ub2e4",
        "vcode": "GAE",
        "vnum": 13
    },
    {
        "bcode": 66,
        "cnum": 3,
        "content": "\ub77c\uc624\ub514\uac8c\uc544 \uad50\ud68c\uc758 \uc0ac\uc790\uc5d0\uac8c \ud3b8\uc9c0\ud558\ub77c \uc544\uba58\uc774\uc2dc\uc694 \ucda9\uc131\ub418\uace0 \ucc38\ub41c \uc99d\uc778\uc774\uc2dc\uc694 \ud558\ub098\ub2d8\uc758 \ucc3d\uc870\uc758 \uadfc\ubcf8\uc774\uc2e0 \uc774\uac00 \uc774\ub974\uc2dc\ub418",
        "vcode": "GAE",
        "vnum": 14
    },
    {
        "bcode": 66,
        "cnum": 3,
        "content": "\ub0b4\uac00 \ub124 \ud589\uc704\ub97c \uc544\ub178\ub2c8 \ub124\uac00 \ucc28\uc9c0\ub3c4 \uc544\ub2c8\ud558\uace0 \ub728\uac81\uc9c0\ub3c4 \uc544\ub2c8\ud558\ub3c4\ub2e4 \ub124\uac00 \ucc28\ub4e0\uc9c0 \ub728\uac81\ub4e0\uc9c0 \ud558\uae30\ub97c \uc6d0\ud558\ub178\ub77c",
        "vcode": "GAE",
        "vnum": 15
    },
    {
        "bcode": 66,
        "cnum": 3,
        "content": "\ub124\uac00 \uc774\uac19\uc774 \ubbf8\uc9c0\uadfc\ud558\uc5ec \ub728\uac81\uc9c0\ub3c4 \uc544\ub2c8\ud558\uace0 \ucc28\uc9c0\ub3c4 \uc544\ub2c8\ud558\ub2c8 \ub0b4 \uc785\uc5d0\uc11c \ub108\ub97c \ud1a0\ud558\uc5ec \ubc84\ub9ac\ub9ac\ub77c",
        "vcode": "GAE",
        "vnum": 16
    },
    {
        "bcode": 66,
        "cnum": 3,
        "content": "\ub124\uac00 \ub9d0\ud558\uae30\ub97c \ub098\ub294 \ubd80\uc790\ub77c \ubd80\uc694\ud558\uc5ec \ubd80\uc871\ud55c \uac83\uc774 \uc5c6\ub2e4 \ud558\ub098 \ub124 \uace4\uace0\ud55c \uac83\uacfc \uac00\ub828\ud55c \uac83\uacfc \uac00\ub09c\ud55c \uac83\uacfc \ub208 \uba3c \uac83\uacfc \ubc8c\uac70\ubc97\uc740 \uac83\uc744 \uc54c\uc9c0 \ubabb\ud558\ub294\ub3c4\ub2e4",
        "vcode": "GAE",
        "vnum": 17
    },
    {
        "bcode": 66,
        "cnum": 3,
        "content": "\ub0b4\uac00 \ub108\ub97c \uad8c\ud558\ub178\ub2c8 \ub0b4\uac8c\uc11c \ubd88\ub85c \uc5f0\ub2e8\ud55c \uae08\uc744 \uc0ac\uc11c \ubd80\uc694\ud558\uac8c \ud558\uace0 \ud770 \uc637\uc744 \uc0ac\uc11c \uc785\uc5b4 \ubc8c\uac70\ubc97\uc740 \uc218\uce58\ub97c \ubcf4\uc774\uc9c0 \uc54a\uac8c \ud558\uace0 \uc548\uc57d\uc744 \uc0ac\uc11c \ub208\uc5d0 \ubc1c\ub77c \ubcf4\uac8c \ud558\ub77c",
        "vcode": "GAE",
        "vnum": 18
    },
    {
        "bcode": 66,
        "cnum": 3,
        "content": "\ubb34\ub987 \ub0b4\uac00 \uc0ac\ub791\ud558\ub294 \uc790\ub97c \ucc45\ub9dd\ud558\uc5ec \uc9d5\uacc4\ud558\ub178\ub2c8 \uadf8\ub7ec\ubbc0\ub85c \ub124\uac00 \uc5f4\uc2ec\uc744 \ub0b4\ub77c \ud68c\uac1c\ud558\ub77c",
        "vcode": "GAE",
        "vnum": 19
    },
    {
        "bcode": 66,
        "cnum": 3,
        "content": "\ubcfc\uc9c0\uc5b4\ub2e4 \ub0b4\uac00 \ubb38 \ubc16\uc5d0 \uc11c\uc11c \ub450\ub4dc\ub9ac\ub178\ub2c8 \ub204\uad6c\ub4e0\uc9c0 \ub0b4 \uc74c\uc131\uc744 \ub4e3\uace0 \ubb38\uc744 \uc5f4\uba74 \ub0b4\uac00 \uadf8\uc5d0\uac8c\ub85c \ub4e4\uc5b4\uac00 \uadf8\uc640 \ub354\ubd88\uc5b4 \uba39\uace0 \uadf8\ub294 \ub098\uc640 \ub354\ubd88\uc5b4 \uba39\uc73c\ub9ac\ub77c",
        "vcode": "GAE",
        "vnum": 20
    },
    {
        "bcode": 66,
        "cnum": 3,
        "content": "\uc774\uae30\ub294 \uadf8\uc5d0\uac8c\ub294 \ub0b4\uac00 \ub0b4 \ubcf4\uc88c\uc5d0 \ud568\uaed8 \uc549\uac8c \ud558\uc5ec \uc8fc\uae30\ub97c \ub0b4\uac00 \uc774\uae30\uace0 \uc544\ubc84\uc9c0 \ubcf4\uc88c\uc5d0 \ud568\uaed8 \uc549\uc740 \uac83\uacfc \uac19\uc774 \ud558\ub9ac\ub77c",
        "vcode": "GAE",
        "vnum": 21
    },
    {
        "bcode": 66,
        "cnum": 3,
        "content": "\uadc0 \uc788\ub294 \uc790\ub294 \uc131\ub839\uc774 \uad50\ud68c\ub4e4\uc5d0\uac8c \ud558\uc2dc\ub294 \ub9d0\uc500\uc744 \ub4e4\uc744\uc9c0\uc5b4\ub2e4",
        "vcode": "GAE",
        "vnum": 22
    }
]