[
    {
        "bcode": 19,
        "cnum": 131,
        "content": "\uc5ec\ud638\uc640\uc5ec \ub0b4 \ub9c8\uc74c\uc774 \uad50\ub9cc\ud558\uc9c0 \uc544\ub2c8\ud558\uace0 \ub0b4 \ub208\uc774 \uc624\ub9cc\ud558\uc9c0 \uc544\ub2c8\ud558\uc624\uba70 \ub0b4\uac00 \ud070 \uc77c\uacfc \uac10\ub2f9\ud558\uc9c0 \ubabb\ud560 \ub180\ub77c\uc6b4 \uc77c\uc744 \ud558\ub824\uace0 \ud798\uc4f0\uc9c0 \uc544\ub2c8\ud558\ub098\uc774\ub2e4",
        "vcode": "GAE",
        "vnum": 1
    },
    {
        "bcode": 19,
        "cnum": 131,
        "content": "\uc2e4\ub85c \ub0b4\uac00 \ub0b4 \uc601\ud63c\uc73c\ub85c \uace0\uc694\ud558\uace0 \ud3c9\uc628\ud558\uac8c \ud558\uae30\ub97c \uc816 \ub5c0 \uc544\uc774\uac00 \uadf8\uc758 \uc5b4\uba38\ub2c8 \ud488\uc5d0 \uc788\uc74c \uac19\uac8c \ud558\uc600\ub098\ub2c8 \ub0b4 \uc601\ud63c\uc774 \uc816 \ub5c0 \uc544\uc774\uc640 \uac19\ub3c4\ub2e4",
        "vcode": "GAE",
        "vnum": 2
    },
    {
        "bcode": 19,
        "cnum": 131,
        "content": "\uc774\uc2a4\ub77c\uc5d8\uc544 \uc9c0\uae08\ubd80\ud130 \uc601\uc6d0\uae4c\uc9c0 \uc5ec\ud638\uc640\ub97c \ubc14\ub784\uc9c0\uc5b4\ub2e4",
        "vcode": "GAE",
        "vnum": 3
    }
]