[
    {
        "bcode": 19,
        "cnum": 97,
        "content": "\uc5ec\ud638\uc640\uaed8\uc11c \ub2e4\uc2a4\ub9ac\uc2dc\ub098\ub2c8 \ub545\uc740 \uc990\uac70\uc6cc\ud558\uba70 \ud5c8\ub2e4\ud55c \uc12c\uc740 \uae30\ubed0\ud560\uc9c0\uc5b4\ub2e4",
        "vcode": "GAE",
        "vnum": 1
    },
    {
        "bcode": 19,
        "cnum": 97,
        "content": "\uad6c\ub984\uacfc \ud751\uc554\uc774 \uadf8\ub97c \ub458\ub800\uace0 \uc758\uc640 \uacf5\ud3c9\uc774 \uadf8\uc758 \ubcf4\uc88c\uc758 \uae30\ucd08\ub85c\ub2e4",
        "vcode": "GAE",
        "vnum": 2
    },
    {
        "bcode": 19,
        "cnum": 97,
        "content": "\ubd88\uc774 \uadf8\uc758 \uc55e\uc5d0\uc11c \ub098\uc640 \uc0ac\ubc29\uc758 \ub300\uc801\ub4e4\uc744 \ubd88\uc0ac\ub974\uc2dc\ub294\ub3c4\ub2e4",
        "vcode": "GAE",
        "vnum": 3
    },
    {
        "bcode": 19,
        "cnum": 97,
        "content": "\uadf8\uc758 \ubc88\uac1c\uac00 \uc138\uacc4\ub97c \ube44\ucd94\ub2c8 \ub545\uc774 \ubcf4\uace0 \ub5a8\uc5c8\ub3c4\ub2e4",
        "vcode": "GAE",
        "vnum": 4
    },
    {
        "bcode": 19,
        "cnum": 97,
        "content": "\uc0b0\ub4e4\uc774 \uc5ec\ud638\uc640\uc758 \uc55e \uace7 \uc628 \ub545\uc758 \uc8fc \uc55e\uc5d0\uc11c \ubc00\ub78d \uac19\uc774 \ub179\uc558\ub3c4\ub2e4",
        "vcode": "GAE",
        "vnum": 5
    },
    {
        "bcode": 19,
        "cnum": 97,
        "content": "\ud558\ub298\uc774 \uadf8\uc758 \uc758\ub97c \uc120\ud3ec\ud558\ub2c8 \ubaa8\ub4e0 \ubc31\uc131\uc774 \uadf8\uc758 \uc601\uad11\uc744 \ubcf4\uc558\ub3c4\ub2e4",
        "vcode": "GAE",
        "vnum": 6
    },
    {
        "bcode": 19,
        "cnum": 97,
        "content": "\uc870\uac01\ud55c \uc2e0\uc0c1\uc744 \uc12c\uae30\uba70 \ud5c8\ubb34\ud55c \uac83\uc73c\ub85c \uc790\ub791\ud558\ub294 \uc790\ub294 \ub2e4 \uc218\uce58\ub97c \ub2f9\ud560 \uac83\uc774\ub77c \ub108\ud76c \uc2e0\ub4e4\uc544 \uc5ec\ud638\uc640\uaed8 \uacbd\ubc30\ud560\uc9c0\uc5b4\ub2e4",
        "vcode": "GAE",
        "vnum": 7
    },
    {
        "bcode": 19,
        "cnum": 97,
        "content": "\uc5ec\ud638\uc640\uc5ec \uc2dc\uc628\uc774 \uc8fc\uc758 \uc2ec\ud310\uc744 \ub4e3\uace0 \uae30\ubed0\ud558\uba70 \uc720\ub2e4\uc758 \ub538\ub4e4\uc774 \uc990\uac70\uc6cc\ud558\uc600\ub098\uc774\ub2e4",
        "vcode": "GAE",
        "vnum": 8
    },
    {
        "bcode": 19,
        "cnum": 97,
        "content": "\uc5ec\ud638\uc640\uc5ec \uc8fc\ub294 \uc628 \ub545 \uc704\uc5d0 \uc9c0\uc874\ud558\uc2dc\uace0 \ubaa8\ub4e0 \uc2e0\ub4e4\ubcf4\ub2e4 \uc704\uc5d0 \uacc4\uc2dc\ub2c8\uc774\ub2e4",
        "vcode": "GAE",
        "vnum": 9
    },
    {
        "bcode": 19,
        "cnum": 97,
        "content": "\uc5ec\ud638\uc640\ub97c \uc0ac\ub791\ud558\ub294 \ub108\ud76c\uc5ec \uc545\uc744 \ubbf8\uc6cc\ud558\ub77c \uadf8\uac00 \uadf8\uc758 \uc131\ub3c4\uc758 \uc601\ud63c\uc744 \ubcf4\uc804\ud558\uc0ac \uc545\uc778\uc758 \uc190\uc5d0\uc11c \uac74\uc9c0\uc2dc\ub290\ub2c8\ub77c",
        "vcode": "GAE",
        "vnum": 10
    },
    {
        "bcode": 19,
        "cnum": 97,
        "content": "\uc758\uc778\uc744 \uc704\ud558\uc5ec \ube5b\uc744 \ubfcc\ub9ac\uace0 \ub9c8\uc74c\uc774 \uc815\uc9c1\ud55c \uc790\ub97c \uc704\ud558\uc5ec \uae30\uc068\uc744 \ubfcc\ub9ac\uc2dc\ub294\ub3c4\ub2e4",
        "vcode": "GAE",
        "vnum": 11
    },
    {
        "bcode": 19,
        "cnum": 97,
        "content": "\uc758\uc778\uc774\uc5ec \ub108\ud76c\ub294 \uc5ec\ud638\uc640\ub85c \ub9d0\ubbf8\uc554\uc544 \uae30\ubed0\ud558\uba70 \uadf8\uc758 \uac70\ub8e9\ud55c \uc774\ub984\uc5d0 \uac10\uc0ac\ud560\uc9c0\uc5b4\ub2e4",
        "vcode": "GAE",
        "vnum": 12
    }
]